check_gh_actions/__init__.py
check_gh_actions/sum.py
check_gh_actions-0.1.2.dist-info/METADATA
check_gh_actions-0.1.2.dist-info/WHEEL
check_gh_actions-0.1.2.dist-info/RECORD
